{
    "tests": [
        {
            "input": {
                "faceColors": ["R", "G", "Y", "O"], 
                "moves": ["B", "b'", "u'", "R"]
            }, 
            "expectedOutput": [
                ["Y", "Y", "Y", "Y", "R", "R", "R", "R", "G"],
                ["G", "R", "O", "O", "O", "G", "G", "G", "G"],
                ["Y", "O", "Y", "G", "O", "O", "G", "G", "Y"],
                ["R", "O", "O", "R", "O", "Y", "Y", "R", "R"]
            ]
        },
        {
            "input": {
                "faceColors": ["W", "B", "G", "O"], 
                "moves": ["R", "r'", "U'", "b"]
            },
            "expectedOutput": [
                ["B", "B", "O", "O", "W", "O", "O", "G", "B"],
                ["W", "B", "G", "G", "B", "G", "G", "W", "W"],
                ["G", "O", "G", "W", "B", "B", "W", "W", "G"],
                ["O", "G", "W", "O", "G", "B", "B", "O", "O"]
            ]
        },
        {
            "input": {
                "faceColors": ["Y", "R", "B", "G"], 
                "moves": ["b'", "L'", "U", "R"]
            },
            "expectedOutput": [
                ["B", "R", "G", "G", "G", "B", "B", "R", "R"],
                ["B", "R", "Y", "Y", "Y", "R", "R", "B", "B"],
                ["Y", "G", "Y", "R", "B", "B", "R", "R", "Y"],
                ["R", "G", "G", "R", "B", "Y", "Y", "G", "G"]
            ]
        },
        {
            "input": {
                "faceColors": ["Y", "O", "B", "W"],
                "moves": ["B'", "L'", "u", "R"]
            },
            "expectedOutput": [
                ["B", "O", "W", "W", "W", "B", "B", "O", "O"],
                ["Y", "O", "B", "B", "O", "B", "B", "Y", "Y"],
                ["B", "W", "B", "O", "Y", "Y", "O", "O", "B"],
                ["W", "Y", "Y", "W", "Y", "O", "O", "W", "W"]
            ]
        },
        {
            "input": {
                "faceColors": ["G", "R", "O", "W"],
                "moves": ["r'", "B'", "L", "u"]
            }, 
            "expectedOutput": [
                ["O", "R", "W", "W", "W", "O", "O", "R", "R"],
                ["R", "G", "O", "O", "O", "R", "R", "G", "G"],
                ["O", "W", "O", "R", "G", "G", "R", "R", "O"],
                ["W", "G", "G", "W", "G", "O", "O", "W", "W"]
            ]
        }
    ]
}